[
  {"title": "Distracted Boyfriend Meme", "url": "https://i.imgflip.com/1ur9b0.jpg"},
  {"title": "Drake Hotline Bling Meme", "url": "https://i.imgflip.com/1otk96.jpg"},
  {"title": "Grumpy Cat Says No", "url": "https://i.imgur.com/3s8zq.jpg"},
  {"title": "Success Kid Fist Pump", "url": "https://i.imgflip.com/1g8my4.jpg"},
  {"title": "Expanding Brain Meme", "url": "https://i.imgflip.com/30b1gx.jpg"},
  {"title": "Sad Affleck Meme", "url": "https://i.imgflip.com/1bgw7c.jpg"},
  {"title": "Spongebob Mocking Meme", "url": "https://i.imgflip.com/1otk96.jpg"},
  {"title": "One Does Not Simply Walk", "url": "https://i.imgflip.com/1ur9b0.jpg"},
  {"title": "Disaster Girl Smirk", "url": "https://i.imgflip.com/1g8my4.jpg"},
  {"title": "This Is Fine Dog", "url": "https://i.kym-cdn.com/photos/images/original/001/105/484/8f9.jpg"},
  {"title": "Kermit Sipping Tea", "url": "https://i.kym-cdn.com/photos/images/original/001/226/048/9d5.jpg"},
  {"title": "Evil Kermit Meme", "url": "https://i.kym-cdn.com/photos/images/original/001/226/048/9d5.jpg"},
  {"title": "Doge Wow Meme", "url": "https://i.kym-cdn.com/photos/images/original/000/581/296/c09.jpg"},
  {"title": "Overly Attached Girlfriend", "url": "https://i.kym-cdn.com/photos/images/original/000/392/685/a9c.jpg"},
  {"title": "Scumbag Steve Meme", "url": "https://i.kym-cdn.com/photos/images/original/000/137/091/1304973746002.jpg"},
  {"title": "Yo Dawg Meme", "url": "https://i.kym-cdn.com/photos/images/original/000/046/277/yo_dawg.jpg"},
  {"title": "First World Problems", "url": "https://i.kym-cdn.com/photos/images/original/000/139/428/First-World-Problems-meme.jpg"},
  {"title": "Philosoraptor Thinks", "url": "https://i.kym-cdn.com/photos/images/original/000/027/248/philosoraptor.jpg"},
  {"title": "Batman Slapping Robin", "url": "https://i.imgflip.com/1bgw7c.jpg"},
  {"title": "Bad Luck Brian", "url": "https://i.kym-cdn.com/photos/images/original/000/293/590/6f6.jpg"},
  {"title": "Change My Mind Meme", "url": "https://i.imgflip.com/24y43o.jpg"},
  {"title": "Is This a Pigeon?", "url": "https://i.kym-cdn.com/photos/images/newsfeed/001/188/090/7c3.png"},
  {"title": "Galaxy Brain Meme", "url": "https://i.imgflip.com/30b1gx.jpg"},
  {"title": "Hide the Pain Harold", "url": "https://i.kym-cdn.com/photos/images/original/000/963/479/4ea.jpg"},
  {"title": "Woman Yelling at Cat", "url": "https://i.kym-cdn.com/photos/images/newsfeed/001/492/575/3e4.jpg"},
  {"title": "Confused Travolta Meme", "url": "https://i.imgur.com/3v7o9.jpg"},
  {"title": "Roll Safe Meme", "url": "https://i.kym-cdn.com/photos/images/original/001/207/424/5c1.jpg"},
  {"title": "Skeptical Baby Meme", "url": "https://i.kym-cdn.com/photos/images/original/000/332/110/82f.jpg"},
  {"title": "Y U No Meme", "url": "https://i.kym-cdn.com/photos/images/original/000/080/047/y-u-no.jpg"},
  {"title": "Awkward Moment Sealion", "url": "https://i.kym-cdn.com/photos/images/original/000/879/138/awkward-moment-sealion.jpg"},
  {"title": "Trollface Meme", "url": "https://i.kym-cdn.com/photos/images/original/000/001/384/Afraid-to-Ask-Andy.jpg"},
  {"title": "Rage Comic Face", "url": "https://i.kym-cdn.com/photos/images/original/000/000/143/rageface.jpg"},
  {"title": "Forever Alone Meme", "url": "https://i.kym-cdn.com/photos/images/original/000/023/397/forever-alone-l.png"},
  {"title": "Me Gusta Meme", "url": "https://i.kym-cdn.com/photos/images/original/000/096/044/me-gusta.jpg"},
  {"title": "Spongebob Caveman Meme", "url": "https://i.kym-cdn.com/photos/images/original/001/254/917/2c3.jpg"},
  {"title": "Distracted Pikachu Meme", "url": "https://i.kym-cdn.com/photos/images/newsfeed/001/505/693/79c.jpg"},
  {"title": "Sad Affleck Pikachu", "url": "https://i.kym-cdn.com/photos/images/original/001/235/965/8b5.jpg"},
  {"title": "Drake Rejects Pokéball", "url": "https://i.imgflip.com/1otk96.jpg"},
  {"title": "Grumpy Cat Pokémon", "url": "https://i.imgur.com/3s8zq.jpg"},
  {"title": "Expanding Pokédex Meme", "url": "https://i.imgflip.com/30b1gx.jpg"},
  {"title": "This Is Fine Charizard", "url": "https://i.kym-cdn.com/photos/images/original/001/105/484/8f9.jpg"},
  {"title": "Kermit as Mewtwo", "url": "https://i.kym-cdn.com/photos/images/original/001/226/048/9d5.jpg"},
  {"title": "Doge Catches Pokémon", "url": "https://i.kym-cdn.com/photos/images/original/000/581/296/c09.jpg"},
  {"title": "Overly Attached Jigglypuff", "url": "https://i.kym-cdn.com/photos/images/original/000/392/685/a9c.jpg"},
  {"title": "Scumbag Trainer Meme", "url": "https://i.kym-cdn.com/photos/images/original/000/137/091/1304973746002.jpg"},
  {"title": "Yo Dawg Pokéball", "url": "https://i.kym-cdn.com/photos/images/original/000/046/277/yo_dawg.jpg"},
  {"title": "Philosoraptor Pokémon", "url": "https://i.kym-cdn.com/photos/images/original/000/027/248/philosoraptor.jpg"},
  {"title": "Batman Slaps Team Rocket", "url": "https://i.imgflip.com/1bgw7c.jpg"},
  {"title": "Bad Luck Ash Ketchum", "url": "https://i.kym-cdn.com/photos/images/original/000/293/590/6f6.jpg"},
  {"title": "Change My Mind Mew", "url": "https://i.imgflip.com/24y43o.jpg"},
  {"title": "Is This a Pidgey?", "url": "https://i.kym-cdn.com/photos/images/newsfeed/001/188/090/7c3.png"},
  {"title": "Galaxy Brain Gengar", "url": "https://i.imgflip.com/30b1gx.jpg"},
  {"title": "Hide the Pain Snorlax", "url": "https://i.kym-cdn.com/photos/images/original/000/963/479/4ea.jpg"},
  {"title": "Woman Yelling at Meowth", "url": "https://i.kym-cdn.com/photos/images/newsfeed/001/492/575/3e4.jpg"},
  {"title": "Confused Squirtle Meme", "url": "https://i.imgur.com/3v7o9.jpg"},
  {"title": "Roll Safe Bulbasaur", "url": "https://i.kym-cdn.com/photos/images/original/001/207/424/5c1.jpg"},
  {"title": "Skeptical Charmander Meme", "url": "https://i.kym-cdn.com/photos/images/original/000/332/110/82f.jpg"},
  {"title": "Y U No Catch Meme", "url": "https://i.kym-cdn.com/photos/images/original/000/080/047/y-u-no.jpg"},
  {"title": "Awkward Psyduck Meme", "url": "https://i.kym-cdn.com/photos/images/original/000/879/138/awkward-moment-sealion.jpg"},
  {"title": "Trollface Magikarp", "url": "https://i.kym-cdn.com/photos/images/original/000/001/384/Afraid-to-Ask-Andy.jpg"},
  {"title": "Rage Comic Squirtle", "url": "https://i.kym-cdn.com/photos/images/original/000/000/143/rageface.jpg"},
  {"title": "Forever Alone Slowpoke", "url": "https://i.kym-cdn.com/photos/images/original/000/023/397/forever-alone-l.png"},
  {"title": "Me Gusta Mewtwo", "url": "https://i.kym-cdn.com/photos/images/original/000/096/044/me-gusta.jpg"},
  {"title": "Spongebob vs Team Rocket", "url": "https://i.kym-cdn.com/photos/images/original/001/254/917/2c3.jpg"},
  {"title": "Distracted Trainer Meme", "url": "https://i.imgflip.com/1ur9b0.jpg"},
  {"title": "Drake Picks Charizard", "url": "https://i.imgflip.com/1otk96.jpg"},
  {"title": "Grumpy Cat Rejects Pokéball", "url": "https://i.imgur.com/3s8zq.jpg"},
  {"title": "Success Kid Catches Shiny", "url": "https://i.imgflip.com/1g8my4.jpg"},
  {"title": "Expanding Brain Pokéfan", "url": "https://i.imgflip.com/30b1gx.jpg"},
  {"title": "Sad Affleck Missing Shiny", "url": "https://i.imgflip.com/1bgw7c.jpg"},
  {"title": "Spongebob Mocking Trainer", "url": "https://i.kym-cdn.com/photos/images/original/001/254/917/2c3.jpg"},
  {"title": "One Does Not Simply Catch Mew", "url": "https://i.imgflip.com/1ur9b0.jpg"},
  {"title": "Disaster Girl Burns Gym", "url": "https://i.imgflip.com/1g8my4.jpg"},
  {"title": "This Is Fine Pokécenter", "url": "https://i.kym-cdn.com/photos/images/original/001/105/484/8f9.jpg"},
  {"title": "Kermit Sips Tea at Gym", "url": "https://i.kym-cdn.com/photos/images/original/001/226/048/9d5.jpg"},
  {"title": "Evil Kermit Trades Pokémon", "url": "https://i.kym-cdn.com/photos/images/original/001/226/048/9d5.jpg"},
  {"title": "Doge Evolves to Arcanine", "url": "https://i.kym-cdn.com/photos/images/original/000/581/296/c09.jpg"},
  {"title": "Overly Attached Pikachu", "url": "https://i.kym-cdn.com/photos/images/original/000/392/685/a9c.jpg"},
  {"title": "Scumbag Gym Leader", "url": "https://i.kym-cdn.com/photos/images/original/000/137/091/1304973746002.jpg"},
  {"title": "Yo Dawg Evolution Stone", "url": "https://i.kym-cdn.com/photos/images/original/000/046/277/yo_dawg.jpg"},
  {"title": "First World Pokéfan Problems", "url": "https://i.kym-cdn.com/photos/images/original/000/139/428/First-World-Problems-meme.jpg"},
  {"title": "Philosoraptor on Legendaries", "url": "https://i.kym-cdn.com/photos/images/original/000/027/248/philosoraptor.jpg"},
  {"title": "Batman Slaps Team Magma", "url": "https://i.imgflip.com/1bgw7c.jpg"},
  {"title": "Bad Luck Missing Mewtwo", "url": "https://i.kym-cdn.com/photos/images/original/000/293/590/6f6.jpg"},
  {"title": "Change My Mind Arceus", "url": "https://i.imgflip.com/24y43o.jpg"},
  {"title": "Is This a Zubat?", "url": "https://i.kym-cdn.com/photos/images/newsfeed/001/188/090/7c3.png"},
  {"title": "Galaxy Brain Alakazam", "url": "https://i.imgflip.com/30b1gx.jpg"},
  {"title": "Hide the Pain Dragonite", "url": "https://i.kym-cdn.com/photos/images/original/000/963/479/4ea.jpg"},
  {"title": "Woman Yelling at Persian", "url": "https://i.kym-cdn.com/photos/images/newsfeed/001/492/575/3e4.jpg"},
  {"title": "Confused Blastoise Meme", "url": "https://i.imgur.com/3v7o9.jpg"},
  {"title": "Roll Safe Venusaur", "url": "https://i.kym-cdn.com/photos/images/original/001/207/424/5c1.jpg"},
  {"title": "Skeptical Eevee Meme", "url": "https://i.kym-cdn.com/photos/images/original/000/332/110/82f.jpg"},
  {"title": "Y U No Evolve Meme", "url": "https://i.kym-cdn.com/photos/images/original/000/080/047/y-u-no.jpg"},
  {"title": "Awkward Lapras Meme", "url": "https://i.kym-cdn.com/photos/images/original/000/879/138/awkward-moment-sealion.jpg"},
  {"title": "Trollface Gyarados", "url": "https://i.kym-cdn.com/photos/images/original/000/001/384/Afraid-to-Ask-Andy.jpg"},
  {"title": "Rage Comic Charmeleon", "url": "https://i.kym-cdn.com/photos/images/original/000/000/143/rageface.jpg"},
  {"title": "Forever Alone Ditto", "url": "https://i.kym-cdn.com/photos/images/original/000/023/397/forever-alone-l.png"},
  {"title": "Me Gusta Snorlax", "url": "https://i.kym-cdn.com/photos/images/original/000/096/044/me-gusta.jpg"},
  {"title": "Spongebob Catches Weedle", "url": "https://i.kym-cdn.com/photos/images/original/001/254/917/2c3.jpg"}
]
